MazeSimulator/MouseClient.py
MouseClient-0.3.dist-info/LICENSE.txt
MouseClient-0.3.dist-info/METADATA
MouseClient-0.3.dist-info/WHEEL
MouseClient-0.3.dist-info/top_level.txt
MouseClient-0.3.dist-info/RECORD
